{
  "title": "Fashion Design Drawing Course",
  "author": "Caroline Tatham",
  "genre": "Fashion",
  "description": "A superb reference book and an ideal instructional textbook for classroom use, this beautifully illustrated guide is organized into units that reflect required courses at leading design colleges. Twenty step-by-step exercises cover methods of finding inspiration, developing observation techniques, and creating fashion drawings in both color and black-and-white media.",
  "yearPublished": 2003
}